scailo_sdk/__init__.py
scailo_sdk/absences_api.py
scailo_sdk/actions_codes_api.py
scailo_sdk/activities_api.py
scailo_sdk/activities_groups_api.py
scailo_sdk/activities_statuses_api.py
scailo_sdk/activities_tags_api.py
scailo_sdk/announcements_api.py
scailo_sdk/asset_indents_api.py
scailo_sdk/associates_api.py
scailo_sdk/attendances_amendments_api.py
scailo_sdk/attendances_api.py
scailo_sdk/bank_accounts_api.py
scailo_sdk/client_streams_api.py
scailo_sdk/clients_api.py
scailo_sdk/components_api.py
scailo_sdk/credit_notes_api.py
scailo_sdk/currencies_api.py
scailo_sdk/debit_notes_api.py
scailo_sdk/departments_api.py
scailo_sdk/equations_families_api.py
scailo_sdk/equations_replaceables_api.py
scailo_sdk/equations_sales_bundles_api.py
scailo_sdk/equations_work_orders_api.py
scailo_sdk/equipments_api.py
scailo_sdk/expenses_api.py
scailo_sdk/families_api.py
scailo_sdk/feedstocks_api.py
scailo_sdk/forms_fields_api.py
scailo_sdk/forms_fields_data_api.py
scailo_sdk/forms_sections_api.py
scailo_sdk/general_settings_api.py
scailo_sdk/general_streams_api.py
scailo_sdk/goals_api.py
scailo_sdk/goods_dispatches_api.py
scailo_sdk/goods_receipts_api.py
scailo_sdk/holidays_api.py
scailo_sdk/infrastructures_api.py
scailo_sdk/inventory_api.py
scailo_sdk/inward_jobs_api.py
scailo_sdk/inward_jobs_free_issue_materials_api.py
scailo_sdk/inward_jobs_free_issue_materials_returns_api.py
scailo_sdk/labels_api.py
scailo_sdk/leaves_adjustments_api.py
scailo_sdk/leaves_logs_api.py
scailo_sdk/leaves_requests_api.py
scailo_sdk/leaves_types_api.py
scailo_sdk/ledgers_api.py
scailo_sdk/locations_api.py
scailo_sdk/login_api.py
scailo_sdk/magic_links_api.py
scailo_sdk/meetings_api.py
scailo_sdk/merchandises_api.py
scailo_sdk/notes_api.py
scailo_sdk/on_duties_api.py
scailo_sdk/outward_jobs_api.py
scailo_sdk/outward_jobs_free_issue_materials_api.py
scailo_sdk/outward_jobs_free_issue_materials_returns_api.py
scailo_sdk/overtimes_api.py
scailo_sdk/payroll_groups_api.py
scailo_sdk/payroll_params_api.py
scailo_sdk-0.2.9.dist-info/licenses/LICENSE
scailo_sdk-0.2.9.dist-info/METADATA
scailo_sdk-0.2.9.dist-info/WHEEL
scailo_sdk-0.2.9.dist-info/top_level.txt
scailo_sdk-0.2.9.dist-info/RECORD
