Metadata-Version: 2.4
Name: scailo_sdk
Version: 0.2.9
Summary: Python SDK for the Scailo API
Home-page: https://github.com/scailo/python-sdk
Author: Pratheek Adidela
Author-email: apratheek@unaxiom.com
License: Apache-2.0
Classifier: Programming Language :: Python :: 3
Classifier: License :: OSI Approved :: Apache Software License
Classifier: Operating System :: OS Independent
Requires-Python: >=3.6
License-File: LICENSE
Requires-Dist: aiohappyeyeballs==2.6.1
Requires-Dist: aiohttp==3.13.2
Requires-Dist: aiosignal==1.4.0
Requires-Dist: annotated-types==0.7.0
Requires-Dist: anyio==4.10.0
Requires-Dist: attrs==25.3.0
Requires-Dist: certifi==2025.8.3
Requires-Dist: connect-python==0.4.2
Requires-Dist: frozenlist==1.7.0
Requires-Dist: googleapis-common-protos==1.70.0
Requires-Dist: grpcio==1.75.0
Requires-Dist: grpcio-tools==1.75.0
Requires-Dist: h11==0.16.0
Requires-Dist: h2==4.3.0
Requires-Dist: hpack==4.1.0
Requires-Dist: httpcore==1.0.9
Requires-Dist: hyperframe==6.1.0
Requires-Dist: idna==3.10
Requires-Dist: multidict==6.6.4
Requires-Dist: propcache==0.3.2
Requires-Dist: protobuf>=6.33.2
Requires-Dist: protogen==0.3.1
Requires-Dist: pydantic==2.11.9
Requires-Dist: pydantic_core==2.33.2
Requires-Dist: setuptools>=80.1.0
Requires-Dist: sniffio==1.3.1
Requires-Dist: starlette==0.48.0
Requires-Dist: types-protobuf>=6.32.1.20251210
Requires-Dist: typing-inspection==0.4.1
Requires-Dist: typing_extensions==4.15.0
Requires-Dist: urllib3==2.5.0
Requires-Dist: yarl==1.20.1
Dynamic: author
Dynamic: author-email
Dynamic: classifier
Dynamic: description
Dynamic: description-content-type
Dynamic: home-page
Dynamic: license
Dynamic: license-file
Dynamic: requires-dist
Dynamic: requires-python
Dynamic: summary
